AUTHORS.rst
CONTRIBUTING.rst
HISTORY.rst
LICENSE
MANIFEST.in
README.rst
setup.cfg
test/test_yafa_grpc.py
yafa_grpc/__init__.py
yafa_grpc/command_line.py
yafa_grpc/data_warehouse_client.py
yafa_grpc/data_warehouse_pb2.py
yafa_grpc/data_warehouse_pb2_grpc.py
yafa_grpc/data_warehouse_server.py
yafa_grpc.egg-info/PKG-INFO
yafa_grpc.egg-info/SOURCES.txt
yafa_grpc.egg-info/dependency_links.txt
yafa_grpc.egg-info/entry_points.txt
yafa_grpc.egg-info/not-zip-safe
yafa_grpc.egg-info/top_level.txt
yafa_grpc-0.1.0.dist-info/AUTHORS.rst
yafa_grpc-0.1.0.dist-info/LICENSE
yafa_grpc-0.1.0.dist-info/METADATA
yafa_grpc-0.1.0.dist-info/WHEEL
yafa_grpc-0.1.0.dist-info/entry_points.txt
yafa_grpc-0.1.0.dist-info/top_level.txt
yafa_grpc-0.1.0.dist-info/RECORD
