Metadata-Version: 2.1
Name: yafa-grpc
Version: 0.1.0
Summary: Stock trading backtesting with grpc
Home-page: https://github.com/gcrowell/yafa_grpc
Author: Graham Crowell
Author-email: graham.crowell@gmail.com
License: MIT
Keywords: yafa_grpc
Platform: UNKNOWN
Classifier: Development Status :: 2 - Pre-Alpha
Classifier: Intended Audience :: Developers
Classifier: License :: OSI Approved :: MIT License
Classifier: Natural Language :: English
Classifier: Programming Language :: Python :: 3
Classifier: Programming Language :: Python :: 3.7
Classifier: Programming Language :: Python :: Implementation :: PyPy
